retrieveStack/__init__.py
retrieveStack/__init__.pyc
retrieveStack/baseFunctions.py
retrieveStack/retrieveEnsemble.py
retrieveStack-0.0.1.dist-info/DESCRIPTION.rst
retrieveStack-0.0.1.dist-info/METADATA
retrieveStack-0.0.1.dist-info/RECORD
retrieveStack-0.0.1.dist-info/WHEEL
retrieveStack-0.0.1.dist-info/metadata.json
retrieveStack-0.0.1.dist-info/top_level.txt
